Workbook

Sheet Sales_Data
A2: Ship Mode | B2: Segment | C2: Country | D2: City | E2: State | F2: Postal Code | G2: Region | H2: Category | I2: Sub-Category | J2: Sales | K2: Quantity | L2: Discount | M2: Profit
A3: Second Class | B3: Consumer | C3: United States | D3: Henderson | E3: Kentucky | F3: 42420 | G3: South | H3: Furniture | I3: Bookcases | J3: 261.96 | K3: 2 | L3: 0 | M3: 41.9136
A4: Second Class | B4: Consumer | C4: United States | D4: Henderson | E4: Kentucky | F4: 42420 | G4: South | H4: Furniture | I4: Chairs | J4: 731.94 | K4: 3 | L4: 0 | M4: 219.582
A5: Second Class | B5: Corporate | C5: United States | D5: Los Angeles | E5: California | F5: 90036 | G5: West | H5: Office Supplies | I5: Labels | J5: 14.62 | K5: 2 | L5: 0 | M5: 6.8714
A6: Standard Class | B6: Consumer | C6: United States | D6: Fort Lauderdale | E6: Florida | F6: 33311 | G6: South | H6: Furniture | I6: Tables | J6: 957.5775 | K6: 5 | L6: 0.45 | M6: -383.031
A7: Standard Class | B7: Consumer | C7: United States | D7: Fort Lauderdale | E7: Florida | F7: 33311 | G7: South | H7: Office Supplies | I7: Storage | J7: 22.368 | K7: 2 | L7: 0.2 | M7: 2.5164
A8: Standard Class | B8: Consumer | C8: United States | D8: Los Angeles | E8: California | F8: 90032 | G8: West | H8: Furniture | I8: Furnishings | J8: 48.86 | K8: 7 | L8: 0 | M8: 14.1694
A9: Standard Class | B9: Consumer | C9: United States | D9: Los Angeles | E9: California | F9: 90032 | G9: West | H9: Office Supplies | I9: Art | J9: 7.28 | K9: 4 | L9: 0 | M9: 1.9656
A10: Standard Class | B10: Consumer | C10: United States | D10: Los Angeles | E10: California | F10: 90032 | G10: West | H10: Technology | I10: Phones | J10: 907.152 | K10: 6 | L10: 0.2 | M10: 90.7152
A11: Standard Class | B11: Consumer | C11: United States | D11: Los Angeles | E11: California | F11: 90032 | G11: West | H11: Office Supplies | I11: Binders | J11: 18.504 | K11: 3 | L11: 0.2 | M11: 5.7825
A12: Standard Class | B12: Consumer | C12: United States | D12: Los Angeles | E12: California | F12: 90032 | G12: West | H12: Office Supplies | I12: Appliances | J12: 114.9 | K12: 5 | L12: 0 | M12: 34.47
A13: Standard Class | B13: Consumer | C13: United States | D13: Los Angeles | E13: California | F13: 90032 | G13: West | H13: Furniture | I13: Tables | J13: 1706.184 | K13: 9 | L13: 0.2 | M13: 85.3092
A14: Standard Class | B14: Consumer | C14: United States | D14: Los Angeles | E14: California | F14: 90032 | G14: West | H14: Technology | I14: Phones | J14: 911.424 | K14: 4 | L14: 0.2 | M14: 68.3568
... A9979: Second Class | B9979: Consumer | C9979: United States | D9979: Westminster | E9979: California | F9979: 92683 | G9979: West | H9979: Office Supplies | I9979: Appliances | J9979: 243.16 | K9979: 2 | L9979: 0 | M9979: 72.948

Sheet Sales_Summary
A1: BASIC SALES SUMMARY
A2: Veda Technology | Day 14 | Task 14 | Data Analytics Track
A4: Dataset | B4: Superstore | C4: Transactions | D4: =COUNT(Sales_Data!J2:J9978) -> 9976 | E4: TOTAL SALES | H4: AVERAGE SALES | K4: TRANSACTION COUNT
E5: =SUM(Sales_Data!J:J) -> 2296195.6 | H5: =AVERAGE(Sales_Data!J:J) -> 230.1489 | K5: =COUNT(Sales_Data!J:J) -> 9977
A6: KPI | B6: VALUE | C6: FORMULA / CHECK
A7: Total Sales | B7: =SUM(Sales_Data!J:J) -> 2296195.6 | C7: SUM(Sales_Data!Sales)
A8: Average Sales | B8: =AVERAGE(Sales_Data!J:J) -> 230.1489 | C8: AVERAGE(Sales_Data!Sales)
A9: Transaction Count | B9: =COUNT(Sales_Data!J:J) -> 9977 | C9: COUNT(Sales_Data!Sales)
A12: VERIFICATION
A13: Sales Records Checked | B13: =COUNT(Sales_Data!J:J) -> 9977 | C13: =COUNT(Sales_Data!J:J) -> 9977
A14: Missing Sales Values | B14: =COUNTBLANK(Sales_Data!J2:J9978) -> 0 | C14: =COUNTBLANK(Sales_Data!J2:J9978) -> 0
A15: Minimum Sale | B15: =MIN(Sales_Data!J2:J9978) -> 0.444 | C15: =MIN(Sales_Data!J2:J9978) -> 0.444
A16: Maximum Sale | B16: =MAX(Sales_Data!J2:J9978) -> 22638.48
A19: BUSINESS INTERPRETATION
A20: Total Sales | B20: Overall revenue generated across all recorded transactions.
A21: Average Sales | B21: Average revenue generated per transaction.
A22: Transaction Count | B22: Total number of sales transactions recorded in the dataset.

Sheet Product_Count_Analysis
A1: Category | B1: Product Count | C1: % of Total
A2: Furniture | B2: =COUNTIF(Sales_Data!H:H,A2) -> 2118 | C2: =B2/SUM($B$2:$B$4) -> 0.21228826
A3: Office Supplies | B3: =COUNTIF(Sales_Data!H:H,A3) -> 6012 | C3: =B3/SUM($B$2:$B$4) -> 0.60258595
A4: Technology | B4: =COUNTIF(Sales_Data!H:H,A4) -> 1847 | C4: =B4/SUM($B$2:$B$4) -> 0.18512579
A6: Largest Category | B6: =INDEX(A2:A4,MATCH(MAX(B2:B4),B2:B4,0)) -> Office Supplies
A8: Key Insight
A9: Office Supplies has the highest product count with 6,012 records, representing approximately 60% of the total records.

Sheet Task_Notes
A1: Veda Technology - Day 14 - Task 14
A3: Objective | B3: Calculate total sales, average sales, and transaction count.
A4: Tool | B4: Microsoft Excel
A5: Dataset | B5: Superstore cleaned dataset
A6: Deliverables | B6: Summary sheet and 3 KPIs
A8: Quality Checks | B8: Verified sales count, missing sales values, minimum sale, and maximum sale.
